orionai/__init__.py
orionai/adapters/__init__.py
orionai/adapters/file_adapter.py
orionai/adapters/pandas_adapter.py
orionai/adapters/polars_adapter.py
orionai/adapters/torch_adapter.py
orionai/cli/__init__.py
orionai/cli/chat.py
orionai/cli/config.py
orionai/cli/main.py
orionai/cli/session.py
orionai/core/__init__.py
orionai/core/aiobject.py
orionai/core/base.py
orionai/core/llm_interface.py
orionai/core/manager.py
orionai/python/__init__.py
orionai/python/aipython.py
orionai/python/lazy_imports.py
orionai/ui/__init__.py
orionai/ui/streamlit_ui.py
orionai/utils/__init__.py
orionai/utils/sandbox.py
orionai/utils/validator.py
orionai-1.0.0.dist-info/licenses/LICENSE
orionai-1.0.0.dist-info/METADATA
orionai-1.0.0.dist-info/WHEEL
orionai-1.0.0.dist-info/entry_points.txt
orionai-1.0.0.dist-info/top_level.txt
orionai-1.0.0.dist-info/RECORD
