Metadata-Version: 2.4
Name: orionai
Version: 1.0.0
Summary: AI-powered Python assistant for natural language coding with CLI and web interface
Home-page: https://github.com/AIMLDev726/OrionAI
Author: AIMLDev726
Author-email: AIMLDev726 <aistudentlearn4@gmail.com>
Maintainer-email: AIMLDev726 <aistudentlearn4@gmail.com>
License: MIT
Project-URL: Homepage, https://github.com/AIMLDev726/OrionAI
Project-URL: Documentation, https://github.com/AIMLDev726/OrionAI/blob/main/docs/
Project-URL: Repository, https://github.com/AIMLDev726/OrionAI
Project-URL: Bug Tracker, https://github.com/AIMLDev726/OrionAI/issues
Project-URL: Changelog, https://github.com/AIMLDev726/OrionAI/blob/main/CHANGELOG.md
Keywords: ai,python,assistant,llm,coding,automation,data-science,machine-learning,natural-language
Classifier: Development Status :: 5 - Production/Stable
Classifier: Intended Audience :: Developers
Classifier: Intended Audience :: Science/Research
Classifier: Intended Audience :: Education
Classifier: License :: OSI Approved :: MIT License
Classifier: Operating System :: OS Independent
Classifier: Programming Language :: Python :: 3
Classifier: Programming Language :: Python :: 3.8
Classifier: Programming Language :: Python :: 3.9
Classifier: Programming Language :: Python :: 3.10
Classifier: Programming Language :: Python :: 3.11
Classifier: Programming Language :: Python :: 3.12
Classifier: Topic :: Scientific/Engineering :: Artificial Intelligence
Classifier: Topic :: Software Development :: Libraries :: Python Modules
Classifier: Topic :: Education
Classifier: Topic :: Utilities
Requires-Python: >=3.8
License-File: LICENSE
Requires-Dist: requests>=2.25.0
Requires-Dist: rich>=10.0.0
Requires-Dist: google-generativeai>=0.3.0
Requires-Dist: openai>=1.0.0
Requires-Dist: anthropic>=0.8.0
Requires-Dist: pyyaml>=6.0.0
Requires-Dist: pandas>=1.3.0
Requires-Dist: numpy>=1.21.0
Requires-Dist: matplotlib>=3.5.0
Requires-Dist: seaborn>=0.11.0
Provides-Extra: data
Requires-Dist: pandas>=1.3.0; extra == "data"
Requires-Dist: numpy>=1.21.0; extra == "data"
Requires-Dist: matplotlib>=3.5.0; extra == "data"
Requires-Dist: seaborn>=0.11.0; extra == "data"
Provides-Extra: ml
Requires-Dist: scikit-learn>=1.0.0; extra == "ml"
Requires-Dist: scipy>=1.7.0; extra == "ml"
Provides-Extra: web
Requires-Dist: beautifulsoup4>=4.10.0; extra == "web"
Requires-Dist: lxml>=4.6.0; extra == "web"
Provides-Extra: ui
Requires-Dist: streamlit>=1.20.0; extra == "ui"
Provides-Extra: dev
Requires-Dist: pytest>=6.0.0; extra == "dev"
Requires-Dist: pytest-cov>=3.0.0; extra == "dev"
Requires-Dist: black>=22.0.0; extra == "dev"
Requires-Dist: isort>=5.0.0; extra == "dev"
Requires-Dist: flake8>=4.0.0; extra == "dev"
Requires-Dist: mypy>=0.900; extra == "dev"
Provides-Extra: all
Requires-Dist: orionai[data,dev,ml,ui,web]; extra == "all"
Dynamic: author
Dynamic: home-page
Dynamic: license-file
Dynamic: requires-python
